puretest/__init__.py
puretest-0.0.1.dist-info/LICENSE
puretest-0.0.1.dist-info/METADATA
puretest-0.0.1.dist-info/WHEEL
puretest-0.0.1.dist-info/top_level.txt
puretest-0.0.1.dist-info/RECORD
